Metadata-Version: 2.1
Name: oreoTO
Version: 0.2
Summary: Giting info for any account in the tiktok
Author: oreoTO
Author-email: zyaahee@gmail.com
Classifier: Programming Language :: Python :: 3
Classifier: Operating System :: OS Independent
Classifier: License :: OSI Approved :: MIT License
